eigmod/ButtonFunktionen.py
eigmod/Graphen2.py
eigmod/__init__.py
eigmod/border_zoom_camera_alt#####.py
eigmod/camera.py
eigmod/check_box.py
eigmod/check_box_collection.py
eigmod/collisionen.py
eigmod/draw_assistance.py
eigmod/draw_text_list.py
eigmod/help_functions.py
eigmod/input_box.py
eigmod/numpy_assistance.py
eigmod/slider.py
eigmod/test.py
eigmod-0.0.19.dist-info/METADATA
eigmod-0.0.19.dist-info/WHEEL
eigmod-0.0.19.dist-info/top_level.txt
eigmod-0.0.19.dist-info/RECORD
