Metadata-Version: 2.1
Name: eigmod
Version: 0.0.19
Summary: UNKNOWN
Home-page: UNKNOWN
Author: felix-95
Author-email: felix.schaefer6@gmx.de
License: UNKNOWN
Keywords: python
Platform: UNKNOWN
Classifier: Development Status :: 1 - Planning
Classifier: Intended Audience :: Developers
Classifier: Programming Language :: Python :: 3
Requires-Dist: pygame
